setup.py
aws_keyring.egg-info/PKG-INFO
aws_keyring.egg-info/SOURCES.txt
aws_keyring.egg-info/dependency_links.txt
aws_keyring.egg-info/entry_points.txt
aws_keyring.egg-info/not-zip-safe
aws_keyring.egg-info/requires.txt
aws_keyring.egg-info/top_level.txt
aws_keys/__init__.py