Metadata-Version: 1.1
Name: aws-keyring
Version: 0.2.4
Summary: Manage AWS credentials in your OS keyring.
Home-page: http://github.com/philipn/aws-keyring/
Author: Philip Neustrom
Author-email: philipn@gmail.com
License: UNKNOWN
Platform: UNKNOWN
Classifier: Development Status :: 3 - Alpha
Classifier: Environment :: Web Environment
Classifier: License :: OSI Approved :: BSD License
Classifier: Operating System :: OS Independent
Classifier: Programming Language :: Python
Classifier: Programming Language :: Python :: 3
Classifier: Programming Language :: Python :: 3 :: Only
